{"cameraMode":{"drawMode":0,"name":"Shaded","section":"Shading Mode"},"sceneLighting":false,"audioPlay":false,"sceneViewState":{"m_AlwaysRefresh":false,"showFog":true,"showSkybox":false,"showFlares":true,"showImageEffects":true,"showParticleSystems":true,"showVisualEffectGraphs":true,"m_FxEnabled":true},"in2DMode":false,"pivot":{"x":701.9725952148438,"y":357.5437316894531,"z":-86.1060791015625},"rotation":{"x":-0.03294724225997925,"y":-0.14579829573631288,"z":0.004857842810451984,"w":-0.9887468814849854},"size":551.9196166992188,"orthographic":false}